{
  "version": "1.0.0",
  "lastUpdated": "2026-01-28T00:00:00Z",
  "saints": [
    {
      "id": "francis-assisi",
      "nameKo": "아시시의 성 프란치스코",
      "nameEn": "Saint Francis of Assisi",
      "nameLatin": "Franciscus Assisiensis",
      "shortName": "프란치스코",
      "feastMonth": 10,
      "feastDay": 4,
      "patronages": ["동물", "환경", "이탈리아", "상인"],
      "patronageCategories": ["cause", "location", "occupation"],
      "biography": "아시시의 성 프란치스코(1181/1182-1226)는 이탈리아의 수도자이자 프란치스코회의 창설자입니다. 부유한 상인의 아들로 태어났으나 모든 것을 버리고 가난과 청빈의 삶을 선택했습니다. 자연과 동물을 사랑하여 '피조물의 찬가'를 지었으며, 가톨릭교회에서 환경 수호성인으로 공경받습니다.",
      "birthYear": 1182,
      "deathYear": 1226,
      "canonizationYear": 1228,
      "initials": "프"
    },
    {
      "id": "andrew-kim",
      "nameKo": "성 김대건 안드레아",
      "nameEn": "Saint Andrew Kim Taegon",
      "nameLatin": "Andreas Kim Taegon",
      "shortName": "김대건",
      "feastMonth": 9,
      "feastDay": 20,
      "patronages": ["한국", "성직자", "한국 천주교회"],
      "patronageCategories": ["location", "occupation"],
      "biography": "성 김대건 안드레아(1821-1846)는 한국 최초의 천주교 사제입니다. 조선 시대 박해 속에서 중국 마카오에서 신학을 공부하고 사제로 서품되었습니다. 귀국 후 선교 활동을 하다가 체포되어 26세의 나이로 순교하였습니다. 1984년 성인품에 올랐습니다.",
      "birthYear": 1821,
      "deathYear": 1846,
      "canonizationYear": 1984,
      "initials": "김"
    },
    {
      "id": "teresa-calcutta",
      "nameKo": "콜카타의 성녀 테레사",
      "nameEn": "Saint Teresa of Calcutta",
      "nameLatin": "Teresia Calcuttensis",
      "shortName": "테레사",
      "feastMonth": 9,
      "feastDay": 5,
      "patronages": ["선교사", "가난한 이들", "세계 청년 대회"],
      "patronageCategories": ["occupation", "situation"],
      "biography": "콜카타의 성녀 테레사(1910-1997)는 마케도니아 출신의 가톨릭 수녀로, 사랑의 선교회를 설립하여 인도 콜카타의 가난한 이들과 병자들을 돌보았습니다. 1979년 노벨 평화상을 수상했으며, 2016년 성인품에 올랐습니다.",
      "birthYear": 1910,
      "deathYear": 1997,
      "canonizationYear": 2016,
      "initials": "테"
    },
    {
      "id": "patrick-ireland",
      "nameKo": "아일랜드의 성 파트리치오",
      "nameEn": "Saint Patrick",
      "nameLatin": "Patricius",
      "shortName": "파트리치오",
      "feastMonth": 3,
      "feastDay": 17,
      "patronages": ["아일랜드", "공학자", "뱀에 물린 사람"],
      "patronageCategories": ["location", "occupation", "situation"],
      "biography": "성 파트리치오(385-461)는 아일랜드의 주보성인입니다. 영국에서 태어났으나 해적에게 납치되어 아일랜드에서 노예 생활을 했습니다. 탈출 후 사제가 되어 아일랜드로 돌아가 그리스도교를 전파했습니다.",
      "birthYear": 385,
      "deathYear": 461,
      "initials": "파"
    },
    {
      "id": "joseph-husband-mary",
      "nameKo": "성 요셉",
      "nameEn": "Saint Joseph",
      "nameLatin": "Iosephus",
      "shortName": "요셉",
      "feastMonth": 3,
      "feastDay": 19,
      "patronages": ["가정", "노동자", "죽어가는 이들", "보편 교회"],
      "patronageCategories": ["situation", "occupation", "cause"],
      "biography": "성 요셉은 복되신 동정 마리아의 남편이자 예수 그리스도의 양부입니다. 목수로서 성실하게 가정을 돌보았으며, 가톨릭교회에서 가장 공경받는 성인 중 한 분입니다. 가정과 노동자, 그리고 보편 교회의 수호성인입니다.",
      "initials": "요"
    },
    {
      "id": "mary-mother-god",
      "nameKo": "하느님의 어머니 복되신 동정 마리아",
      "nameEn": "Blessed Virgin Mary",
      "nameLatin": "Beata Maria Virgo",
      "shortName": "성모 마리아",
      "feastMonth": 1,
      "feastDay": 1,
      "patronages": ["전 인류", "교회", "모든 국가"],
      "patronageCategories": ["cause", "location"],
      "biography": "복되신 동정 마리아는 예수 그리스도의 어머니이십니다. 가톨릭교회에서 가장 높이 공경받으시며, 하느님의 어머니(Theotokos), 평생 동정녀, 원죄 없이 잉태되신 분으로 선포되었습니다.",
      "initials": "마"
    },
    {
      "id": "peter-apostle",
      "nameKo": "사도 성 베드로",
      "nameEn": "Saint Peter the Apostle",
      "nameLatin": "Petrus Apostolus",
      "shortName": "베드로",
      "feastMonth": 6,
      "feastDay": 29,
      "patronages": ["교황", "어부", "열쇠 제조공", "로마"],
      "patronageCategories": ["occupation", "location"],
      "biography": "사도 성 베드로는 예수 그리스도의 수제자이자 초대 교황입니다. 어부 시몬이었으나 예수님의 부르심을 받아 '반석'이라는 뜻의 베드로라는 이름을 받았습니다. 로마에서 순교하여 바티칸 언덕에 묻혔습니다.",
      "deathYear": 64,
      "initials": "베"
    },
    {
      "id": "paul-apostle",
      "nameKo": "사도 성 바오로",
      "nameEn": "Saint Paul the Apostle",
      "nameLatin": "Paulus Apostolus",
      "shortName": "바오로",
      "feastMonth": 6,
      "feastDay": 29,
      "patronages": ["신학자", "작가", "출판업자", "언론인"],
      "patronageCategories": ["occupation"],
      "biography": "사도 성 바오로는 처음에 사울이라는 이름으로 그리스도인을 박해했으나, 다마스쿠스로 가는 길에서 부활하신 예수님을 만나 회심했습니다. 이후 이방인들에게 복음을 전하는 사도가 되어 많은 서간을 남겼습니다.",
      "birthYear": 5,
      "deathYear": 64,
      "initials": "바"
    },
    {
      "id": "augustine-hippo",
      "nameKo": "히포의 성 아우구스티노",
      "nameEn": "Saint Augustine of Hippo",
      "nameLatin": "Aurelius Augustinus Hipponensis",
      "shortName": "아우구스티노",
      "feastMonth": 8,
      "feastDay": 28,
      "patronages": ["신학자", "인쇄공", "양조업자"],
      "patronageCategories": ["occupation"],
      "biography": "히포의 성 아우구스티노(354-430)는 서방 교회의 위대한 교부이자 신학자입니다. 방탕한 젊은 시절을 보냈으나 어머니 성녀 모니카의 기도와 성 암브로시오의 영향으로 회심하여 세례를 받았습니다. '고백록'과 '신국론' 등을 저술했습니다.",
      "birthYear": 354,
      "deathYear": 430,
      "initials": "아"
    },
    {
      "id": "thomas-aquinas",
      "nameKo": "성 토마스 아퀴나스",
      "nameEn": "Saint Thomas Aquinas",
      "nameLatin": "Thomas Aquinas",
      "shortName": "토마스",
      "feastMonth": 1,
      "feastDay": 28,
      "patronages": ["학생", "대학교", "철학자", "신학자"],
      "patronageCategories": ["situation", "occupation"],
      "biography": "성 토마스 아퀴나스(1225-1274)는 도미니코회 수도자이자 중세 최고의 신학자입니다. '신학대전'을 저술하여 아리스토텔레스 철학과 그리스도교 신학을 종합했습니다. 교회 박사로 선포되었습니다.",
      "birthYear": 1225,
      "deathYear": 1274,
      "canonizationYear": 1323,
      "initials": "토"
    },
    {
      "id": "therese-lisieux",
      "nameKo": "아기 예수의 성녀 데레사",
      "nameEn": "Saint Therese of Lisieux",
      "nameLatin": "Teresia a Iesu Infante",
      "shortName": "소화 데레사",
      "feastMonth": 10,
      "feastDay": 1,
      "patronages": ["선교사", "꽃집", "프랑스"],
      "patronageCategories": ["occupation", "location"],
      "biography": "아기 예수의 성녀 데레사(1873-1897)는 프랑스의 가르멜 수녀입니다. '작은 길'이라 불리는 영성을 실천하여 일상의 작은 일에서 하느님 사랑을 실천했습니다. 24세에 결핵으로 선종했으나 '영혼의 이야기'가 널리 읽히며 교회 박사로 선포되었습니다.",
      "birthYear": 1873,
      "deathYear": 1897,
      "canonizationYear": 1925,
      "initials": "데"
    },
    {
      "id": "luke-evangelist",
      "nameKo": "복음사가 성 루카",
      "nameEn": "Saint Luke the Evangelist",
      "nameLatin": "Lucas Evangelista",
      "shortName": "루카",
      "feastMonth": 10,
      "feastDay": 18,
      "patronages": ["의사", "화가", "외과의"],
      "patronageCategories": ["occupation"],
      "biography": "복음사가 성 루카는 루카 복음서와 사도행전의 저자입니다. 시리아 안티오키아 출신의 의사였으며, 바오로 사도의 동료로서 선교 여행을 함께 했습니다. 전통적으로 성모 마리아의 초상화를 그린 최초의 화가로 알려져 있습니다.",
      "initials": "루"
    }
  ]
}
